iliaD/__init__.py
iliaD/cypter.py
iliaD/iliaD.py
iliaD/pictures.py
iliaD/util.py
iliaDownloader-1.1.5.dist-info/LICENSE
iliaDownloader-1.1.5.dist-info/METADATA
iliaDownloader-1.1.5.dist-info/WHEEL
iliaDownloader-1.1.5.dist-info/entry_points.txt
iliaDownloader-1.1.5.dist-info/top_level.txt
iliaDownloader-1.1.5.dist-info/RECORD
