Metadata-Version: 2.1
Name: iliaDownloader
Version: 1.1.5
Summary: A simple ilias downloader.
Home-page: https://github.com/cold-soda-jay/iliaD
Author: Joe
Author-email: linukaszkr@gmail.com
License: MIT
Platform: UNKNOWN
Classifier: License :: OSI Approved :: GNU General Public License v3 (GPLv3)
Classifier: Programming Language :: Python
Classifier: Programming Language :: Python :: 3
Classifier: Programming Language :: Python :: 3.6
Classifier: Programming Language :: Python :: Implementation :: CPython
Classifier: Programming Language :: Python :: Implementation :: PyPy
Requires-Python: >=3.6.0
